KAGraph/KAGraph.py
KAGraph/__init__.py
KAGraph-2024.2.26.2.dist-info/LICENSE
KAGraph-2024.2.26.2.dist-info/METADATA
KAGraph-2024.2.26.2.dist-info/WHEEL
KAGraph-2024.2.26.2.dist-info/top_level.txt
KAGraph-2024.2.26.2.dist-info/RECORD
