Metadata-Version: 2.1
Name: KAGraph
Version: 2024.2.26.2
Summary: Easy and Fast Implementation for Graph Class (AI Universidad Panamericana - Dr Barrera)
Author: Enrique Gómez Tagle
Author-email: Enrique Gómez Tagle <kikinacademy@gmail.com>
Classifier: Programming Language :: Python :: 3
Classifier: License :: OSI Approved :: MIT License
Classifier: Operating System :: OS Independent
License-File: LICENSE
